MANIFEST.in
README.rst
setup.py
jingtum_sdk.egg-info/PKG-INFO
jingtum_sdk.egg-info/SOURCES.txt
jingtum_sdk.egg-info/dependency_links.txt
jingtum_sdk.egg-info/requires.txt
jingtum_sdk.egg-info/top_level.txt
jingtum_sdk.egg-info/zip-safe
jingtumsdk/__init__.py
jingtumsdk/account.py
jingtumsdk/config.json
jingtumsdk/config.py
jingtumsdk/logger.py
jingtumsdk/operation.py
jingtumsdk/serialize.py
jingtumsdk/server.py
jingtumsdk/sign.py