Metadata-Version: 1.1
Name: jingtum-sdk
Version: 0.9.0
Summary: Python routines for the Jingtum payment network
Home-page: http://git.jingtum.com/Delida/jingtum_sdk_python.git
Author: Frank Xu
Author-email: xuqing@jdwtgroup.com 
License: BSD
Platform: UNKNOWN
Classifier: Development Status :: 3 - Alpha
Classifier: Programming Language :: Python :: 2.7
Classifier: License :: OSI Approved :: BSD License
